redis_manager/__init__.py
redis_manager/config.py
redis_manager/prometheus_metrics.py
redis_manager/redis_connection.py
redis_manager/redis_manager.py
redis_manager-0.1.1.dist-info/LICENSE
redis_manager-0.1.1.dist-info/METADATA
redis_manager-0.1.1.dist-info/WHEEL
redis_manager-0.1.1.dist-info/top_level.txt
redis_manager-0.1.1.dist-info/RECORD
